{
  "appPageId" : "7d00f507-10bc-4d1c-b9f5-8db832e53e7e",
  "componentName" : "siteforce:sldsOneColLayout",
  "dataProviders" : [ ],
  "id" : "e424fcd9-122e-4af2-a768-99e2813ca59c",
  "label" : "Account Management",
  "regions" : [ {
    "id" : "220d6b53-1a1c-4c3e-8ef1-a3eb7931aa66",
    "regionName" : "header",
    "type" : "region"
  }, {
    "components" : [ {
      "componentAttributes" : {
        "tabsetConfig" : {
          "UUID" : "ae8aeb08-8696-4cbd-adb5-2268a8cbdb39",
          "activeTab" : "tab1",
          "tabs" : [ {
            "UUID" : "c6b67638-2096-4981-9567-948bb04fd708",
            "allowGuestUser" : false,
            "locked" : false,
            "seedComponents" : [ {
              "attributes" : {
                "customTitle" : "Members",
                "parentRecordId" : "{!CurrentUser.accountId}",
                "relatedListName" : "Users",
                "showBreadCrumbs" : "false",
                "showCustomTitle" : "true",
                "showManualRefreshButton" : "false",
                "showRowNumbers" : "false"
              },
              "fqn" : "forceCommunity:relatedList"
            } ],
            "tabKey" : "tab1",
            "tabName" : "Members"
          }, {
            "UUID" : "b052d612-6c83-4adf-94bd-c4c2369beab1",
            "allowGuestUser" : false,
            "locked" : false,
            "seedComponents" : [ {
              "attributes" : {
                "recordId" : "{!CurrentUser.accountId}"
              },
              "fqn" : "forceCommunity:accountBrandRecord"
            } ],
            "tabKey" : "tab2",
            "tabName" : "Branding"
          } ],
          "useOverflowMenu" : false
        }
      },
      "componentName" : "forceCommunity:tabLayout",
      "id" : "ae8aeb08-8696-4cbd-adb5-2268a8cbdb39",
      "regions" : [ {
        "components" : [ {
          "componentAttributes" : {
            "customTitle" : "Members",
            "parentRecordId" : "{!CurrentUser.accountId}",
            "relatedListName" : "Users",
            "showBreadCrumbs" : false,
            "showCustomTitle" : true,
            "showManualRefreshButton" : false,
            "showRowNumbers" : false
          },
          "componentName" : "forceCommunity:relatedList",
          "id" : "c4190566-c233-47f9-949a-b070fd2523bf",
          "renderPriority" : "NEUTRAL",
          "renditionMap" : { },
          "type" : "component"
        } ],
        "id" : "c6b67638-2096-4981-9567-948bb04fd708",
        "regionLabel" : "Members",
        "regionName" : "tab1",
        "renditionMap" : { },
        "type" : "region"
      }, {
        "components" : [ {
          "componentAttributes" : {
            "recordId" : "{!CurrentUser.accountId}"
          },
          "componentName" : "forceCommunity:accountBrandRecord",
          "id" : "5644b971-34e0-4ec4-b7a4-c41be5364496",
          "renderPriority" : "NEUTRAL",
          "renditionMap" : { },
          "type" : "component"
        } ],
        "id" : "b052d612-6c83-4adf-94bd-c4c2369beab1",
        "regionLabel" : "Branding",
        "regionName" : "tab2",
        "renditionMap" : { },
        "type" : "region"
      } ],
      "renderPriority" : "NEUTRAL",
      "renditionMap" : { },
      "type" : "component"
    } ],
    "id" : "a5288d5a-6f6f-4fae-bef5-1b379c56a0fb",
    "regionName" : "content",
    "type" : "region"
  }, {
    "id" : "8c85c4d5-8a76-4123-ac28-92e274a4754b",
    "regionName" : "footer",
    "type" : "region"
  }, {
    "components" : [ {
      "componentAttributes" : {
        "customHeadTags" : "",
        "description" : "",
        "title" : "Account Management"
      },
      "componentName" : "forceCommunity:seoAssistant",
      "id" : "1faa7657-86f0-4875-99c4-704471e15991",
      "renditionMap" : { },
      "type" : "component"
    } ],
    "id" : "38d77a06-a7f0-4976-aaf2-4521781d9976",
    "regionName" : "sfdcHiddenRegion",
    "type" : "region"
  } ],
  "themeLayoutType" : "Inner",
  "type" : "view",
  "viewType" : "account-management"
}